setup.py
def_bot/__init__.py
def_bot/commands.py
def_bot/def_bot.py
def_bot.egg-info/PKG-INFO
def_bot.egg-info/SOURCES.txt
def_bot.egg-info/dependency_links.txt
def_bot.egg-info/entry_points.txt
def_bot.egg-info/requires.txt
def_bot.egg-info/top_level.txt