Metadata-Version: 1.1
Name: def-bot
Version: 0.1.6
Summary: The original @def_bot implementation
Home-page: https://git.hso.rocks/hso/def
Author: José Sazo
Author-email: jose.sazo@gmail.com
License: UNKNOWN
Download-URL: https://git.hso.rocks/hso/def/archive/0.1.6.tar.gz
Platform: UNKNOWN
Classifier: Development Status :: 3 - Alpha
Classifier: Programming Language :: Python :: 3
Classifier: Programming Language :: Python :: 3.4
